Screenton_maker_rs-0.1.5.dist-info/METADATA
Screenton_maker_rs-0.1.5.dist-info/WHEEL
screenton_maker/__init__.py
screenton_maker/screenton_maker.cpython-311-s390x-linux-gnu.so
Screenton_maker_rs-0.1.5.dist-info/RECORD
