Metadata-Version: 2.3
Name: Screenton_maker_rs
Version: 0.1.5
Classifier: Programming Language :: Rust
Classifier: Programming Language :: Python :: Implementation :: CPython
Classifier: Programming Language :: Python :: Implementation :: PyPy
Classifier: Topic :: Scientific/Engineering :: Image Processing
Requires-Dist: numpy >=1.16.0
Requires-Python: >=3.8
